pxia/__init__.py
pxia/auto.py
pxia/modeling_ann.py
pxia/modeling_gpt2.py
pxia-0.2.0.dist-info/LICENSE
pxia-0.2.0.dist-info/METADATA
pxia-0.2.0.dist-info/WHEEL
pxia-0.2.0.dist-info/top_level.txt
pxia-0.2.0.dist-info/RECORD
